MANIFEST.in
entry-points.ini
requirements.txt
setup.py
pytex/__init__.py
pytex/logging.py
pytex/settings.py
pytex/subcommands.py
pytex.egg-info/PKG-INFO
pytex.egg-info/SOURCES.txt
pytex.egg-info/dependency_links.txt
pytex.egg-info/entry_points.txt
pytex.egg-info/requires.txt
pytex.egg-info/top_level.txt
pytex/commands/__init__.py
pytex/commands/building.py
pytex/commands/diff.py
pytex/commands/init.py
pytex/commands/templates.py
pytex/monitors/__init__.py
pytex/monitors/base.py
pytex/monitors/fsevents.py
pytex/monitors/pyinotify.py
pytex/scripts/__init__.py
pytex/scripts/pytex.py