Metadata-Version: 1.0
Name: pytex
Version: 0.1a
Summary: Command line utility to ease working on LaTeX documents.
Home-page: https://github.com/garetjax/pytex
Author: Jonathan Stoppani
Author-email: jonathan@stoppani.name
License: MIT
Download-URL: https://github.com/garetjax/pytex/tarball/0.1a
Platform: UNKNOWN
